sourceplus_sdk/__init__.py
sourceplus_sdk/libs.py
sourceplus_sdk/main.py
sourceplus_sdk-0.0.3.dist-info/LICENSE.txt
sourceplus_sdk-0.0.3.dist-info/METADATA
sourceplus_sdk-0.0.3.dist-info/WHEEL
sourceplus_sdk-0.0.3.dist-info/entry_points.txt
sourceplus_sdk-0.0.3.dist-info/top_level.txt
sourceplus_sdk-0.0.3.dist-info/RECORD
