Metadata-Version: 2.1
Name: sourceplus-sdk
Version: 0.0.3
Summary: Search, curate, and enrich collections for AI training.
Home-page: https://github.com/Spawning-Inc/sourceplus-sdk/
Author: Nick Padgett
Author-email: nick@spawning.ai
License: MIT
Project-URL: Documentation, https://sourceplus-sdk.readthedocs.io/en/latest/
Project-URL: Source, https://github.com/Spawning-Inc/sourceplus-sdk
Project-URL: Tracker, https://github.com/Spawning-Inc/sourceplus-sdk/issues
Project-URL: Changelog, https://sourceplus-sdk.readthedocs.io/en/latest/changelog.html
Platform: any
Classifier: Development Status :: 4 - Beta
Classifier: Programming Language :: Python
Requires-Python: >=3.8
License-File: LICENSE.txt
Requires-Dist: httpx
Requires-Dist: pandas
Requires-Dist: fastparquet
Requires-Dist: aiofiles
Requires-Dist: importlib-metadata ; python_version < "3.8"
Provides-Extra: testing
Requires-Dist: setuptools ; extra == 'testing'
Requires-Dist: pytest ; extra == 'testing'
Requires-Dist: pytest-cov ; extra == 'testing'
